pptagent/__init__.py
pptagent/agent.py
pptagent/apis.py
pptagent/induct.py
pptagent/llms.py
pptagent/mcp_server.py
pptagent/model_utils.py
pptagent/multimodal.py
pptagent/ppteval.py
pptagent/pptgen.py
pptagent/utils.py
pptagent/document/__init__.py
pptagent/document/doc_utils.py
pptagent/document/document.py
pptagent/document/element.py
pptagent/presentation/__init__.py
pptagent/presentation/layout.py
pptagent/presentation/presentation.py
pptagent/presentation/shapes.py
pptagent/prompts/ask_category.txt
pptagent/prompts/caption.txt
pptagent/prompts/category_split.txt
pptagent/prompts/lengthy_rewrite.txt
pptagent/prompts/document/heading_extract.txt
pptagent/prompts/document/markdown_image_caption.txt
pptagent/prompts/document/markdown_table_caption.txt
pptagent/prompts/document/merge_metadata.txt
pptagent/prompts/document/section_summary.txt
pptagent/prompts/ppteval/ppteval_coherence.txt
pptagent/prompts/ppteval/ppteval_content.txt
pptagent/prompts/ppteval/ppteval_describe_content.txt
pptagent/prompts/ppteval/ppteval_describe_style.txt
pptagent/prompts/ppteval/ppteval_extract.txt
pptagent/prompts/ppteval/ppteval_style.txt
pptagent/resource/pic_placeholder.png
pptagent/response/__init__.py
pptagent/response/induct.py
pptagent/response/outline.py
pptagent/response/pptgen.py
pptagent/response/response_utils.py
pptagent/roles/agent.yaml
pptagent/roles/coder.yaml
pptagent/roles/content_organizer.yaml
pptagent/roles/doc_extractor.yaml
pptagent/roles/editor.yaml
pptagent/roles/layout_selector.yaml
pptagent/roles/planner.yaml
pptagent/roles/schema_extractor.yaml
pptagent/templates/beamer/description.txt
pptagent/templates/beamer/image_stats.json
pptagent/templates/beamer/slide_induction.json
pptagent/templates/beamer/source.pptx
pptagent/templates/cip/description.txt
pptagent/templates/cip/image_stats.json
pptagent/templates/cip/slide_induction.json
pptagent/templates/cip/source.pptx
pptagent/templates/default/description.txt
pptagent/templates/default/image_stats.json
pptagent-0.2.18.dist-info/METADATA
pptagent-0.2.18.dist-info/WHEEL
pptagent-0.2.18.dist-info/entry_points.txt
pptagent-0.2.18.dist-info/top_level.txt
pptagent-0.2.18.dist-info/RECORD
