Metadata-Version: 2.4
Name: pptagent
Version: 0.2.18
Summary: PPTAgent, a tool for utilizing LLMs to generate PowerPoint presentations from documents.
Author-email: Hao Zheng <wszh712811@gmail.com>
License-Expression: MIT
Project-URL: Homepage, https://github.com/icip-cas/PPTAgent
Project-URL: Bug Tracker, https://github.com/icip-cas/PPTAgent/issues
Keywords: presentation,powerpoint,ppt,llm,ai,document-processing
Classifier: Development Status :: 4 - Beta
Classifier: Intended Audience :: Developers
Classifier: Intended Audience :: Science/Research
Classifier: Programming Language :: Python :: 3
Classifier: Topic :: Office/Business :: Office Suites
Classifier: Topic :: Scientific/Engineering :: Artificial Intelligence
Requires-Python: >=3.11
Requires-Dist: aiometer
Requires-Dist: aiofiles
Requires-Dist: aiohttp
Requires-Dist: beautifulsoup4
Requires-Dist: filelock
Requires-Dist: fastapi[all]
Requires-Dist: fastmcp>=2.10.0
Requires-Dist: func_argparse
Requires-Dist: html2image
Requires-Dist: jinja2
Requires-Dist: json_repair
Requires-Dist: jsonlines
Requires-Dist: lxml
Requires-Dist: mcp>=1.14.0
Requires-Dist: mistune
Requires-Dist: numpy<2.0.0
Requires-Dist: oaib
Requires-Dist: openai>=1.107.3
Requires-Dist: opencv-python-headless
Requires-Dist: openpyxl
Requires-Dist: pdf2image
Requires-Dist: pillow
Requires-Dist: pydantic>=2.10.0
Requires-Dist: PyYAML
Requires-Dist: python-Levenshtein
Requires-Dist: python-multipart
Requires-Dist: pptagent-pptx>=0.0.1
Requires-Dist: pytest
Requires-Dist: pytest-asyncio
Requires-Dist: pytest-xdist
Requires-Dist: rich
Requires-Dist: socksio
Requires-Dist: tenacity
Requires-Dist: uvicorn
Provides-Extra: full
Requires-Dist: transformers<4.50.0; extra == "full"
Requires-Dist: fasttext; extra == "full"
Requires-Dist: einops; extra == "full"
Requires-Dist: peft; extra == "full"
Requires-Dist: huggingface_hub; extra == "full"
Requires-Dist: timm; extra == "full"
